{"name":"Colin reviews our range of products","id":"browse-the-catalog;colin-reviews-our-range-of-products","testSteps":[{"number":1,"description":"Given Colin has logged onto the application","duration":20576,"startTime":"2021-11-07T15:02:15.768079894Z[Etc/UTC]","screenshots":[{"screenshot":"fb410c75017cb64e4be16494b0350a904d433f82b154581654e6e2b1ff5840aa.png","timeStamp":1636297356344}],"result":"SUCCESS","precondition":false,"level":0,"children":[{"number":2,"description":"Colin opens the https://www.saucedemo.com","duration":1837,"startTime":"2021-11-07T15:02:27.187715654Z[Etc/UTC]","screenshots":[{"screenshot":"f0a5176c327625555e054b2216c42dfa0c1adbef28e37a5aa67544ac69d73f76.png","timeStamp":1636297348066},{"screenshot":"5cb8bb2ca20a5faf13b87bb3fa18c0750c8f023a6c014907aa7d3ce1106d57b3.png","timeStamp":1636297349025}],"result":"SUCCESS","precondition":false,"level":1},{"number":3,"description":"Colin logs in with username standard_user and password secret_sauce","duration":7071,"startTime":"2021-11-07T15:02:29.246309098Z[Etc/UTC]","screenshots":[{"screenshot":"5cb8bb2ca20a5faf13b87bb3fa18c0750c8f023a6c014907aa7d3ce1106d57b3.png","timeStamp":1636297349966},{"screenshot":"fb410c75017cb64e4be16494b0350a904d433f82b154581654e6e2b1ff5840aa.png","timeStamp":1636297356317}],"result":"SUCCESS","precondition":false,"level":1,"children":[{"number":4,"description":"Colin enters \u0027standard_user\u0027 into the \u0027Username\u0027 field","duration":1223,"startTime":"2021-11-07T15:02:29.976328617Z[Etc/UTC]","screenshots":[{"screenshot":"5cb8bb2ca20a5faf13b87bb3fa18c0750c8f023a6c014907aa7d3ce1106d57b3.png","timeStamp":1636297350003},{"screenshot":"f4cc9f5781b67424e93d7f4653ad3008cff3ef5de46c07336e6c232310f06bd6.png","timeStamp":1636297351196}],"result":"SUCCESS","precondition":false,"level":2},{"number":5,"description":"Colin enters \u0027secret_sauce\u0027 into the \u0027Password\u0027 field","duration":1281,"startTime":"2021-11-07T15:02:31.203241309Z[Etc/UTC]","screenshots":[{"screenshot":"f4cc9f5781b67424e93d7f4653ad3008cff3ef5de46c07336e6c232310f06bd6.png","timeStamp":1636297351217},{"screenshot":"45b25160035bf5fceecae0af54c3da98bc204e785b6039140f23bafc1eaddae7.png","timeStamp":1636297352484}],"result":"SUCCESS","precondition":false,"level":2},{"number":6,"description":"Colin clicks on \u0027Login\u0027 button","duration":3808,"startTime":"2021-11-07T15:02:32.503798997Z[Etc/UTC]","screenshots":[{"screenshot":"45b25160035bf5fceecae0af54c3da98bc204e785b6039140f23bafc1eaddae7.png","timeStamp":1636297352527},{"screenshot":"fb410c75017cb64e4be16494b0350a904d433f82b154581654e6e2b1ff5840aa.png","timeStamp":1636297356312}],"result":"SUCCESS","precondition":false,"level":2}]}]},{"number":7,"description":"When Colin is browsing the product catalog","duration":3379,"startTime":"2021-11-07T15:02:36.344956284Z[Etc/UTC]","screenshots":[{"screenshot":"fb410c75017cb64e4be16494b0350a904d433f82b154581654e6e2b1ff5840aa.png","timeStamp":1636297359724}],"result":"SUCCESS","precondition":false,"level":0,"children":[{"number":8,"description":"Colin opens the https://www.saucedemo.com/inventory.html","duration":3343,"startTime":"2021-11-07T15:02:36.360958384Z[Etc/UTC]","screenshots":[{"screenshot":"fb410c75017cb64e4be16494b0350a904d433f82b154581654e6e2b1ff5840aa.png","timeStamp":1636297359704}],"result":"SUCCESS","precondition":false,"level":1}]},{"number":9,"description":"Then he should be presented with 6 products","duration":2117,"startTime":"2021-11-07T15:02:39.725038494Z[Etc/UTC]","screenshots":[{"screenshot":"fb410c75017cb64e4be16494b0350a904d433f82b154581654e6e2b1ff5840aa.png","timeStamp":1636297361842}],"result":"SUCCESS","precondition":false,"level":0,"children":[{"number":10,"description":"he should see a collection of the \u0027inventory_item_name\u0027 element that is of size: \u003c6\u003e","duration":2022,"startTime":"2021-11-07T15:02:39.812231582Z[Etc/UTC]","screenshots":[{"screenshot":"fb410c75017cb64e4be16494b0350a904d433f82b154581654e6e2b1ff5840aa.png","timeStamp":1636297361834}],"result":"SUCCESS","precondition":false,"level":1}]}],"userStory":{"id":"browse-the-catalog","storyName":"Browse the catalog","displayName":"Browse the catalog","path":"catalog/browse_catalog.feature","type":"feature"},"featureTag":{"name":"Catalog/Browse the catalog","type":"feature","displayName":"Catalog/Browse the catalog"},"title":"Colin reviews our range of products","description":"","backgroundTitle":"","backgroundDescription":"","tags":[{"name":"singlebrowser","type":"tag","displayName":"singlebrowser"},{"name":"Catalog/Browse the catalog","type":"feature","displayName":"Browse the catalog"},{"name":"Catalog","type":"capability","displayName":"Catalog"}],"startTime":"2021-11-07T15:02:14.767497Z[Etc/UTC]","duration":27090,"rule":{"name":"Catalog should show our top 6 products","description":""},"projectKey":"","sessionId":"f2ac3425e662ed98dc23dd804c5fa46b","driver":"chrome:colin","isManualTestingUpToDate":false,"manual":false,"testSource":"Cucumber","actors":[{"name":"Colin","can":["browse the web"]}],"result":"SUCCESS"}