{"name":"Colin removes an item from the cart on the product catalog page 2","id":"managing-the-cart;colin-removes-an-item-from-the-cart-on-the-product-catalog-page-2","testSteps":[{"number":1,"description":"Given Colin has logged onto the application","duration":1881,"startTime":"2021-11-18T17:49:06.751103136Z[Etc/UTC]","screenshots":[{"screenshot":"1bd1268f1e1be5f3bf96bd82ecbea1d53f437139494bd2415be950dd44c0cc85.png","timeStamp":1637257747805},{"screenshot":"1bd1268f1e1be5f3bf96bd82ecbea1d53f437139494bd2415be950dd44c0cc85.png","timeStamp":1637257748632}],"result":"SUCCESS","precondition":false,"level":0},{"number":2,"description":"Given Colin has the following item in his cart:\n| Sauce Labs Backpack |\n| Sauce Labs Bike Light |","duration":702,"startTime":"2021-11-18T17:49:08.633806735Z[Etc/UTC]","screenshots":[{"screenshot":"1bd1268f1e1be5f3bf96bd82ecbea1d53f437139494bd2415be950dd44c0cc85.png","timeStamp":1637257749335}],"result":"SUCCESS","precondition":false,"level":0},{"number":3,"description":"And Colin is browsing the product catalog","duration":1126,"startTime":"2021-11-18T17:49:09.336947462Z[Etc/UTC]","screenshots":[{"screenshot":"a556b5d1f9b97c14590cd961a00a44fe107adcc7d8e16d75e6a802989a752fda.png","timeStamp":1637257750463}],"result":"SUCCESS","precondition":false,"level":0,"children":[{"number":4,"description":"Colin opens the https://www.saucedemo.com/inventory.html","duration":1107,"startTime":"2021-11-18T17:49:09.352607781Z[Etc/UTC]","screenshots":[{"screenshot":"a556b5d1f9b97c14590cd961a00a44fe107adcc7d8e16d75e6a802989a752fda.png","timeStamp":1637257750460}],"result":"SUCCESS","precondition":false,"level":1}]},{"number":5,"description":"When he removes \"Sauce Labs Backpack\" from the cart","duration":1244,"startTime":"2021-11-18T17:49:10.464180932Z[Etc/UTC]","screenshots":[{"screenshot":"7cc166dd0c8f7fd86ff4054c5cccba7b769ed3ac54c0e4f37b7d404e17c77682.png","timeStamp":1637257751708}],"result":"SUCCESS","precondition":false,"level":0,"children":[{"number":6,"description":"he clicks on \u0027Remove\u0027 button","duration":1226,"startTime":"2021-11-18T17:49:10.478988533Z[Etc/UTC]","screenshots":[{"screenshot":"7cc166dd0c8f7fd86ff4054c5cccba7b769ed3ac54c0e4f37b7d404e17c77682.png","timeStamp":1637257751701}],"result":"SUCCESS","precondition":false,"level":1}]},{"number":7,"description":"Then the cart item count should be 1","duration":900,"startTime":"2021-11-18T17:49:11.709548515Z[Etc/UTC]","screenshots":[{"screenshot":"7cc166dd0c8f7fd86ff4054c5cccba7b769ed3ac54c0e4f37b7d404e17c77682.png","timeStamp":1637257752610}],"result":"SUCCESS","precondition":false,"level":0,"children":[{"number":8,"description":"he should see text of the \u0027shopping_cart_badge\u0027 element that is equal to: \u003c1\u003e","duration":888,"startTime":"2021-11-18T17:49:11.713747367Z[Etc/UTC]","screenshots":[{"screenshot":"7cc166dd0c8f7fd86ff4054c5cccba7b769ed3ac54c0e4f37b7d404e17c77682.png","timeStamp":1637257752601}],"result":"SUCCESS","precondition":false,"level":1}]}],"userStory":{"id":"managing-the-cart","storyName":"Managing the cart","displayName":"Managing the cart","path":"cart/managing_the_cart.feature","type":"feature"},"featureTag":{"name":"Cart/Managing the cart","type":"feature","displayName":"Cart/Managing the cart"},"title":"Colin removes an item from the cart on the product catalog page 2","description":"","backgroundTitle":"","backgroundDescription":"","tags":[{"name":"singlebrowser","type":"tag","displayName":"singlebrowser"},{"name":"Cart","type":"capability","displayName":"Cart"},{"name":"resetappstate","type":"tag","displayName":"resetappstate"},{"name":"Cart/Managing the cart","type":"feature","displayName":"Managing the cart"}],"startTime":"2021-11-18T17:49:06.733853977Z[Etc/UTC]","duration":6076,"rule":{"name":"Customer can remove items from their cart","description":""},"projectKey":"","sessionId":"4e3893d5c2338edb44560452cb007eca","driver":"chrome:colin","isManualTestingUpToDate":false,"manual":false,"testSource":"Cucumber","actors":[{"name":"Colin","can":["browse the web"],"has":["swaglabs.actions.cart.AShoppingCart@79982bcc"]}],"result":"SUCCESS"}