{"name":"Colin confirms his order and is told that the items have been dispatched","id":"completing-a-purchase;colin-confirms-his-order-and-is-told-that-the-items-have-been-dispatched","testSteps":[{"number":1,"description":"Given Colin has logged onto the application","duration":342,"startTime":"2022-02-25T14:48:00.400713299Z[Etc/UTC]","screenshots":[{"screenshot":"2c9f6c3cc758ebe1f6c68833e53f0d2004f20e295807ebb1cbc6196c205b7f26.png","timeStamp":1645800480535},{"screenshot":"312d4a83f36c90641129f23ebf8afd0aac4c1c0bfc4cf021fcaaa271827764f0.png","timeStamp":1645800480742}],"result":"SUCCESS","precondition":false,"level":0,"children":[{"number":2,"description":"Colin opens the browser at https://www.saucedemo.com","duration":34,"startTime":"2022-02-25T14:48:00.546507388Z[Etc/UTC]","screenshots":[{"screenshot":"2c9f6c3cc758ebe1f6c68833e53f0d2004f20e295807ebb1cbc6196c205b7f26.png","timeStamp":1645800480548},{"screenshot":"2c9f6c3cc758ebe1f6c68833e53f0d2004f20e295807ebb1cbc6196c205b7f26.png","timeStamp":1645800480581}],"result":"SUCCESS","precondition":false,"level":1}]},{"number":3,"description":"Given Colin has the following item in his cart:\n| Sauce Labs Backpack |\n| Sauce Labs Bolt T-Shirt |","duration":11,"startTime":"2022-02-25T14:48:00.744233775Z[Etc/UTC]","screenshots":[{"screenshot":"312d4a83f36c90641129f23ebf8afd0aac4c1c0bfc4cf021fcaaa271827764f0.png","timeStamp":1645800480755}],"result":"SUCCESS","precondition":false,"level":0},{"number":4,"description":"When he checks out his cart providing his personal details","duration":1094,"startTime":"2022-02-25T14:48:00.755802752Z[Etc/UTC]","screenshots":[{"screenshot":"4a6b280c6601c4c628832c55e513ea8b03f4f86ba7075790e138aeae8c1a8f7b.png","timeStamp":1645800481850}],"result":"SUCCESS","precondition":false,"level":0,"children":[{"number":5,"description":"he opens the browser at https://www.saucedemo.com/checkout-step-one.html","duration":205,"startTime":"2022-02-25T14:48:00.760733757Z[Etc/UTC]","screenshots":[{"screenshot":"ffbbc4ec0dcbbbc3305bcfeabb807dfeccb913a9af992adb962007ffb0929ade.png","timeStamp":1645800480965}],"result":"SUCCESS","precondition":false,"level":1},{"number":6,"description":"he provides personal details: CustomerDetails[firstName\u003dColin, lastName\u003dMacColin, postCode\u003d123-ABC]","duration":880,"startTime":"2022-02-25T14:48:00.966946881Z[Etc/UTC]","screenshots":[{"screenshot":"ffbbc4ec0dcbbbc3305bcfeabb807dfeccb913a9af992adb962007ffb0929ade.png","timeStamp":1645800480969},{"screenshot":"4a6b280c6601c4c628832c55e513ea8b03f4f86ba7075790e138aeae8c1a8f7b.png","timeStamp":1645800481847}],"result":"SUCCESS","precondition":false,"level":1,"children":[{"number":7,"description":"he enters \u0027Colin\u0027 into \u0027First Name\u0027 field","duration":213,"startTime":"2022-02-25T14:48:00.969801326Z[Etc/UTC]","screenshots":[{"screenshot":"ffbbc4ec0dcbbbc3305bcfeabb807dfeccb913a9af992adb962007ffb0929ade.png","timeStamp":1645800480972},{"screenshot":"2338ffa5301b4d5d64239fc3edaa32a56635341f5d3a004e6d50b7ff756f0151.png","timeStamp":1645800481183}],"result":"SUCCESS","precondition":false,"level":2},{"number":8,"description":"he enters \u0027MacColin\u0027 into \u0027Last Name\u0027 field","duration":214,"startTime":"2022-02-25T14:48:01.183885298Z[Etc/UTC]","screenshots":[{"screenshot":"2338ffa5301b4d5d64239fc3edaa32a56635341f5d3a004e6d50b7ff756f0151.png","timeStamp":1645800481187},{"screenshot":"a81ad35e7b24af53dbed794ecc6cfd4285bb0826765db5e3eab8e32ab7b3f236.png","timeStamp":1645800481398}],"result":"SUCCESS","precondition":false,"level":2},{"number":9,"description":"he enters \u0027123-ABC\u0027 into \u0027Zip/Postal Code\u0027 field","duration":217,"startTime":"2022-02-25T14:48:01.399165247Z[Etc/UTC]","screenshots":[{"screenshot":"a81ad35e7b24af53dbed794ecc6cfd4285bb0826765db5e3eab8e32ab7b3f236.png","timeStamp":1645800481402},{"screenshot":"b4a06bf964d85e6f034e133ba27a6b20209fbc37aaf78136f77d421ffc282352.png","timeStamp":1645800481615}],"result":"SUCCESS","precondition":false,"level":2},{"number":10,"description":"he clicks on \u0027Continue\u0027 button","duration":227,"startTime":"2022-02-25T14:48:01.617544136Z[Etc/UTC]","screenshots":[{"screenshot":"b4a06bf964d85e6f034e133ba27a6b20209fbc37aaf78136f77d421ffc282352.png","timeStamp":1645800481620},{"screenshot":"4a6b280c6601c4c628832c55e513ea8b03f4f86ba7075790e138aeae8c1a8f7b.png","timeStamp":1645800481844}],"result":"SUCCESS","precondition":false,"level":2}]}]},{"number":11,"description":"And he confirms his order","duration":228,"startTime":"2022-02-25T14:48:01.850354347Z[Etc/UTC]","screenshots":[{"screenshot":"b62c3fff2be59f28f0210fa22c7469b9c2d560e69b315c3eba92e4565767123f.png","timeStamp":1645800482079}],"result":"SUCCESS","precondition":false,"level":0,"children":[{"number":12,"description":"he clicks on \u0027Finish\u0027 button","duration":221,"startTime":"2022-02-25T14:48:01.853046295Z[Etc/UTC]","screenshots":[{"screenshot":"b62c3fff2be59f28f0210fa22c7469b9c2d560e69b315c3eba92e4565767123f.png","timeStamp":1645800482074}],"result":"SUCCESS","precondition":false,"level":1}]},{"number":13,"description":"Then he should be informed \"Your order has been dispatched\"","duration":31,"startTime":"2022-02-25T14:48:02.079584226Z[Etc/UTC]","screenshots":[{"screenshot":"b62c3fff2be59f28f0210fa22c7469b9c2d560e69b315c3eba92e4565767123f.png","timeStamp":1645800482111}],"result":"SUCCESS","precondition":false,"level":0,"children":[{"number":14,"description":"he should see Confirmation message with text value that contains: \u003c[Your order has been dispatched]\u003e","duration":25,"startTime":"2022-02-25T14:48:02.083060559Z[Etc/UTC]","screenshots":[{"screenshot":"b62c3fff2be59f28f0210fa22c7469b9c2d560e69b315c3eba92e4565767123f.png","timeStamp":1645800482108}],"result":"SUCCESS","precondition":false,"level":1}]}],"userStory":{"id":"completing-a-purchase","storyName":"Completing a purchase","displayName":"Completing a purchase","path":"purchases/completing_a_purchase.feature","type":"feature"},"featureTag":{"name":"Purchases/Completing a purchase","type":"feature","displayName":"Purchases/Completing a purchase"},"title":"Colin confirms his order and is told that the items have been dispatched","description":"","backgroundTitle":"","backgroundDescription":"","tags":[{"name":"singlebrowser","type":"tag","displayName":"singlebrowser"},{"name":"Purchases","type":"capability","displayName":"Purchases"},{"name":"resetappstate","type":"tag","displayName":"resetappstate"},{"name":"tax","type":"tag","displayName":"tax"},{"name":"Purchases/Completing a purchase","type":"feature","displayName":"Completing a purchase"}],"startTime":"2022-02-25T14:48:00.397910953Z[Etc/UTC]","duration":1779,"rule":{"name":"Customers should be informed that their order has been placed","description":""},"projectKey":"","sessionId":"622994d98ce0082ac77806aba6025c8c","driver":"chrome:colin","isManualTestingUpToDate":false,"manual":false,"testSource":"Cucumber","actors":[{"name":"Colin","can":["browse the web"],"has":["swaglabs.actions.cart.AShoppingCart@509520a5"]}],"result":"SUCCESS"}