{"name":"Colin purchases two items and sees them both appear in the purchase summary","id":"completing-a-purchase;colin-purchases-two-items-and-sees-them-both-appear-in-the-purchase-summary","testSteps":[{"number":1,"description":"Given Colin has logged onto the application","duration":235,"startTime":"2022-02-16T10:15:19.700891371Z[Etc/UTC]","screenshots":[{"screenshot":"b5f607acb31fce0c9f2ed50e58cfb804811628b4e08ddeb993d68f622c20f928.png","timeStamp":1645006519702},{"screenshot":"312d4a83f36c90641129f23ebf8afd0aac4c1c0bfc4cf021fcaaa271827764f0.png","timeStamp":1645006519936}],"result":"SUCCESS","precondition":false,"level":0,"children":[{"number":2,"description":"Colin opens the https://www.saucedemo.com","duration":184,"startTime":"2022-02-16T10:15:19.715137852Z[Etc/UTC]","screenshots":[{"screenshot":"b5f607acb31fce0c9f2ed50e58cfb804811628b4e08ddeb993d68f622c20f928.png","timeStamp":1645006519717},{"screenshot":"312d4a83f36c90641129f23ebf8afd0aac4c1c0bfc4cf021fcaaa271827764f0.png","timeStamp":1645006519899}],"result":"SUCCESS","precondition":false,"level":1}]},{"number":3,"description":"Given Colin has the following items in his cart:\n| Sauce Labs Backpack |\n| Sauce Labs Bolt T-Shirt |","duration":143,"startTime":"2022-02-16T10:15:19.936718555Z[Etc/UTC]","screenshots":[{"screenshot":"312d4a83f36c90641129f23ebf8afd0aac4c1c0bfc4cf021fcaaa271827764f0.png","timeStamp":1645006520080}],"result":"SUCCESS","precondition":false,"level":0},{"number":4,"description":"When he checks out his cart providing his personal details","duration":1180,"startTime":"2022-02-16T10:15:20.081106882Z[Etc/UTC]","screenshots":[{"screenshot":"4a6b280c6601c4c628832c55e513ea8b03f4f86ba7075790e138aeae8c1a8f7b.png","timeStamp":1645006521261}],"result":"SUCCESS","precondition":false,"level":0,"children":[{"number":5,"description":"he opens the https://www.saucedemo.com/checkout-step-one.html","duration":204,"startTime":"2022-02-16T10:15:20.087181959Z[Etc/UTC]","screenshots":[{"screenshot":"ffbbc4ec0dcbbbc3305bcfeabb807dfeccb913a9af992adb962007ffb0929ade.png","timeStamp":1645006520291}],"result":"SUCCESS","precondition":false,"level":1},{"number":6,"description":"he provides personal details: CustomerDetails[firstName\u003dColin, lastName\u003dMacColin, postCode\u003d123-ABC]","duration":965,"startTime":"2022-02-16T10:15:20.292542657Z[Etc/UTC]","screenshots":[{"screenshot":"ffbbc4ec0dcbbbc3305bcfeabb807dfeccb913a9af992adb962007ffb0929ade.png","timeStamp":1645006520294},{"screenshot":"4a6b280c6601c4c628832c55e513ea8b03f4f86ba7075790e138aeae8c1a8f7b.png","timeStamp":1645006521258}],"result":"SUCCESS","precondition":false,"level":1,"children":[{"number":7,"description":"he enters \u0027Colin\u0027 into \u0027First Name\u0027 field","duration":225,"startTime":"2022-02-16T10:15:20.295600196Z[Etc/UTC]","screenshots":[{"screenshot":"ffbbc4ec0dcbbbc3305bcfeabb807dfeccb913a9af992adb962007ffb0929ade.png","timeStamp":1645006520298},{"screenshot":"2338ffa5301b4d5d64239fc3edaa32a56635341f5d3a004e6d50b7ff756f0151.png","timeStamp":1645006520521}],"result":"SUCCESS","precondition":false,"level":2},{"number":8,"description":"he enters \u0027MacColin\u0027 into \u0027Last Name\u0027 field","duration":232,"startTime":"2022-02-16T10:15:20.522199163Z[Etc/UTC]","screenshots":[{"screenshot":"2338ffa5301b4d5d64239fc3edaa32a56635341f5d3a004e6d50b7ff756f0151.png","timeStamp":1645006520525},{"screenshot":"a81ad35e7b24af53dbed794ecc6cfd4285bb0826765db5e3eab8e32ab7b3f236.png","timeStamp":1645006520754}],"result":"SUCCESS","precondition":false,"level":2},{"number":9,"description":"he enters \u0027123-ABC\u0027 into \u0027Zip/Postal Code\u0027 field","duration":235,"startTime":"2022-02-16T10:15:20.755511215Z[Etc/UTC]","screenshots":[{"screenshot":"a81ad35e7b24af53dbed794ecc6cfd4285bb0826765db5e3eab8e32ab7b3f236.png","timeStamp":1645006520758},{"screenshot":"b4a06bf964d85e6f034e133ba27a6b20209fbc37aaf78136f77d421ffc282352.png","timeStamp":1645006520990}],"result":"SUCCESS","precondition":false,"level":2},{"number":10,"description":"he clicks on \u0027Continue\u0027 button","duration":254,"startTime":"2022-02-16T10:15:20.992271710Z[Etc/UTC]","screenshots":[{"screenshot":"b4a06bf964d85e6f034e133ba27a6b20209fbc37aaf78136f77d421ffc282352.png","timeStamp":1645006520995},{"screenshot":"4a6b280c6601c4c628832c55e513ea8b03f4f86ba7075790e138aeae8c1a8f7b.png","timeStamp":1645006521247}],"result":"SUCCESS","precondition":false,"level":2}]}]},{"number":11,"description":"Then he should be presented with a summary of his purchase including:\n| Qty | Description | Price |\n| 1 | Sauce Labs Backpack | $29.99 |\n| 1 | Sauce Labs Bolt T-Shirt | $15.99 |","duration":285,"startTime":"2022-02-16T10:15:21.261494016Z[Etc/UTC]","screenshots":[{"screenshot":"4a6b280c6601c4c628832c55e513ea8b03f4f86ba7075790e138aeae8c1a8f7b.png","timeStamp":1645006521547}],"result":"SUCCESS","precondition":false,"level":0},{"number":12,"description":"And the total price should be:\n| Item total | Tax | Total |\n| $45.98 | $3.68 | $49.66 |","duration":256,"startTime":"2022-02-16T10:15:21.548038242Z[Etc/UTC]","screenshots":[{"screenshot":"4a6b280c6601c4c628832c55e513ea8b03f4f86ba7075790e138aeae8c1a8f7b.png","timeStamp":1645006521804}],"result":"SUCCESS","precondition":false,"level":0,"children":[{"number":13,"description":"he should see text of element located by .summary_subtotal_label that is equal to: \u003c\"$45.98\"\u003e","duration":29,"startTime":"2022-02-16T10:15:21.552198394Z[Etc/UTC]","screenshots":[{"screenshot":"4a6b280c6601c4c628832c55e513ea8b03f4f86ba7075790e138aeae8c1a8f7b.png","timeStamp":1645006521582}],"result":"SUCCESS","precondition":false,"level":1},{"number":14,"description":"he should see text of element located by .summary_tax_label that is equal to: \u003c\"$3.68\"\u003e","duration":180,"startTime":"2022-02-16T10:15:21.583932896Z[Etc/UTC]","screenshots":[{"screenshot":"4a6b280c6601c4c628832c55e513ea8b03f4f86ba7075790e138aeae8c1a8f7b.png","timeStamp":1645006521764}],"result":"SUCCESS","precondition":false,"level":1},{"number":15,"description":"he should see text of element located by .summary_total_label that is equal to: \u003c\"$49.66\"\u003e","duration":34,"startTime":"2022-02-16T10:15:21.765745666Z[Etc/UTC]","screenshots":[{"screenshot":"4a6b280c6601c4c628832c55e513ea8b03f4f86ba7075790e138aeae8c1a8f7b.png","timeStamp":1645006521800}],"result":"SUCCESS","precondition":false,"level":1}]}],"userStory":{"id":"completing-a-purchase","storyName":"Completing a purchase","displayName":"Completing a purchase","path":"purchases/completing_a_purchase.feature","type":"feature"},"featureTag":{"name":"Purchases/Completing a purchase","type":"feature","displayName":"Purchases/Completing a purchase"},"title":"Colin purchases two items and sees them both appear in the purchase summary","description":"","backgroundTitle":"","backgroundDescription":"","tags":[{"name":"singlebrowser","type":"tag","displayName":"singlebrowser"},{"name":"Purchases","type":"capability","displayName":"Purchases"},{"name":"resetappstate","type":"tag","displayName":"resetappstate"},{"name":"tax","type":"tag","displayName":"tax"},{"name":"Purchases/Completing a purchase","type":"feature","displayName":"Completing a purchase"}],"startTime":"2022-02-16T10:15:19.698156437Z[Etc/UTC]","duration":2171,"rule":{"name":"Customers should see a summary of their order before they complete their purchase","description":""},"projectKey":"","sessionId":"a84b8ab879075753213bc35471da5737","driver":"chrome:colin","isManualTestingUpToDate":false,"manual":false,"testSource":"Cucumber","actors":[{"name":"Colin","can":["browse the web"],"has":["swaglabs.actions.cart.AShoppingCart@56f8032"]}],"result":"SUCCESS"}