{"name":"Colin removes an item from the cart overview","id":"managing-the-cart;colin-removes-an-item-from-the-cart-overview","testSteps":[{"number":1,"description":"Given Colin has logged onto the application","duration":2021,"startTime":"2022-02-12T09:35:07.579295175Z[Etc/UTC]","screenshots":[{"screenshot":"312d4a83f36c90641129f23ebf8afd0aac4c1c0bfc4cf021fcaaa271827764f0.png","timeStamp":1644658509600}],"result":"SUCCESS","precondition":false,"level":0,"children":[{"number":2,"description":"Colin opens the https://www.saucedemo.com","duration":421,"startTime":"2022-02-12T09:35:09.132245390Z[Etc/UTC]","screenshots":[{"screenshot":"d398faa00b048f2d4af37add34086dd711d451a615b7587b44f60e25f41f9182.png","timeStamp":1644658509240},{"screenshot":"312d4a83f36c90641129f23ebf8afd0aac4c1c0bfc4cf021fcaaa271827764f0.png","timeStamp":1644658509553}],"result":"SUCCESS","precondition":false,"level":1}]},{"number":3,"description":"Given Colin has the following item in his cart:\n| Sauce Labs Backpack |\n| Sauce Labs Bike Light |","duration":129,"startTime":"2022-02-12T09:35:09.601199443Z[Etc/UTC]","screenshots":[{"screenshot":"312d4a83f36c90641129f23ebf8afd0aac4c1c0bfc4cf021fcaaa271827764f0.png","timeStamp":1644658509730}],"result":"SUCCESS","precondition":false,"level":0},{"number":4,"description":"And Colin has opened the shopping cart","duration":229,"startTime":"2022-02-12T09:35:09.731322895Z[Etc/UTC]","screenshots":[{"screenshot":"7ea92f8e896339c5c8791bdb356b55da58574bacca4aa753141efd9e41c34ba1.png","timeStamp":1644658509960}],"result":"SUCCESS","precondition":false,"level":0,"children":[{"number":5,"description":"Colin opens the https://www.saucedemo.com/cart.html","duration":223,"startTime":"2022-02-12T09:35:09.734457335Z[Etc/UTC]","screenshots":[{"screenshot":"7ea92f8e896339c5c8791bdb356b55da58574bacca4aa753141efd9e41c34ba1.png","timeStamp":1644658509957}],"result":"SUCCESS","precondition":false,"level":1}]},{"number":6,"description":"When he removes \"Sauce Labs Backpack\" from the cart","duration":1287,"startTime":"2022-02-12T09:35:09.961111112Z[Etc/UTC]","screenshots":[{"screenshot":"462ede654114dbfdec5561bbe0a5b4b35c66cc9e794538f0dc9db7690ca13c6c.png","timeStamp":1644658511248}],"result":"SUCCESS","precondition":false,"level":0,"children":[{"number":7,"description":"he clicks on \u0027Remove\u0027 button","duration":1281,"startTime":"2022-02-12T09:35:09.964093250Z[Etc/UTC]","screenshots":[{"screenshot":"462ede654114dbfdec5561bbe0a5b4b35c66cc9e794538f0dc9db7690ca13c6c.png","timeStamp":1644658511245}],"result":"SUCCESS","precondition":false,"level":1}]},{"number":8,"description":"Then he should see the following items:\n| Sauce Labs Bike Light |","duration":176,"startTime":"2022-02-12T09:35:11.249332508Z[Etc/UTC]","screenshots":[{"screenshot":"462ede654114dbfdec5561bbe0a5b4b35c66cc9e794538f0dc9db7690ca13c6c.png","timeStamp":1644658511425}],"result":"SUCCESS","precondition":false,"level":0,"children":[{"number":9,"description":"he should see text of each of the \u0027inventory_item_name\u0027 element that contains: \u003c[Sauce Labs Bike Light]\u003e","duration":34,"startTime":"2022-02-12T09:35:11.258276921Z[Etc/UTC]","screenshots":[{"screenshot":"462ede654114dbfdec5561bbe0a5b4b35c66cc9e794538f0dc9db7690ca13c6c.png","timeStamp":1644658511292}],"result":"SUCCESS","precondition":false,"level":1}]}],"userStory":{"id":"managing-the-cart","storyName":"Managing the cart","displayName":"Managing the cart","path":"cart/managing_the_cart.feature","type":"feature"},"featureTag":{"name":"Cart/Managing the cart","type":"feature","displayName":"Cart/Managing the cart"},"title":"Colin removes an item from the cart overview","description":"","backgroundTitle":"","backgroundDescription":"","tags":[{"name":"Cart","type":"capability","displayName":"Cart"},{"name":"Cart/Managing the cart","type":"feature","displayName":"Managing the cart"}],"startTime":"2022-02-12T09:35:07.577147047Z[Etc/UTC]","duration":3855,"rule":{"name":"Customer can remove items from their cart","description":""},"projectKey":"","sessionId":"e3a212a9df91cfd26352e7ce8b5cf2cf","driver":"chrome:colin","isManualTestingUpToDate":false,"manual":false,"testSource":"Cucumber","actors":[{"name":"Colin","can":["browse the web"],"has":["swaglabs.actions.cart.AShoppingCart@782f56af"]}],"result":"SUCCESS"}