{"name":"Colin removes an item from the cart overview","id":"managing-the-cart;colin-removes-an-item-from-the-cart-overview","testSteps":[{"number":1,"description":"Given Colin has logged onto the application","duration":1108,"startTime":"2022-02-25T14:48:24.733077825Z[Etc/UTC]","screenshots":[{"screenshot":"312d4a83f36c90641129f23ebf8afd0aac4c1c0bfc4cf021fcaaa271827764f0.png","timeStamp":1645800505841}],"result":"SUCCESS","precondition":false,"level":0,"children":[{"number":2,"description":"Colin opens the browser at https://www.saucedemo.com","duration":884,"startTime":"2022-02-25T14:48:24.741183473Z[Etc/UTC]","screenshots":[{"screenshot":"312d4a83f36c90641129f23ebf8afd0aac4c1c0bfc4cf021fcaaa271827764f0.png","timeStamp":1645800505625}],"result":"SUCCESS","precondition":false,"level":1}]},{"number":3,"description":"Given Colin has the following item in his cart:\n| Sauce Labs Backpack |\n| Sauce Labs Bike Light |","duration":11,"startTime":"2022-02-25T14:48:25.842248637Z[Etc/UTC]","screenshots":[{"screenshot":"312d4a83f36c90641129f23ebf8afd0aac4c1c0bfc4cf021fcaaa271827764f0.png","timeStamp":1645800505853}],"result":"SUCCESS","precondition":false,"level":0},{"number":4,"description":"And Colin has opened the shopping cart","duration":235,"startTime":"2022-02-25T14:48:25.853673822Z[Etc/UTC]","screenshots":[{"screenshot":"7ea92f8e896339c5c8791bdb356b55da58574bacca4aa753141efd9e41c34ba1.png","timeStamp":1645800506089}],"result":"SUCCESS","precondition":false,"level":0,"children":[{"number":5,"description":"Colin opens the browser at https://www.saucedemo.com/cart.html","duration":229,"startTime":"2022-02-25T14:48:25.856709665Z[Etc/UTC]","screenshots":[{"screenshot":"7ea92f8e896339c5c8791bdb356b55da58574bacca4aa753141efd9e41c34ba1.png","timeStamp":1645800506086}],"result":"SUCCESS","precondition":false,"level":1}]},{"number":6,"description":"When he removes \"Sauce Labs Backpack\" from the cart","duration":1280,"startTime":"2022-02-25T14:48:26.089717077Z[Etc/UTC]","screenshots":[{"screenshot":"462ede654114dbfdec5561bbe0a5b4b35c66cc9e794538f0dc9db7690ca13c6c.png","timeStamp":1645800507370}],"result":"SUCCESS","precondition":false,"level":0,"children":[{"number":7,"description":"he clicks on \u0027Remove\u0027 button","duration":1275,"startTime":"2022-02-25T14:48:26.092542624Z[Etc/UTC]","screenshots":[{"screenshot":"462ede654114dbfdec5561bbe0a5b4b35c66cc9e794538f0dc9db7690ca13c6c.png","timeStamp":1645800507367}],"result":"SUCCESS","precondition":false,"level":1}]},{"number":8,"description":"Then he should see the following items:\n| Sauce Labs Bike Light |","duration":40,"startTime":"2022-02-25T14:48:27.370569456Z[Etc/UTC]","screenshots":[{"screenshot":"462ede654114dbfdec5561bbe0a5b4b35c66cc9e794538f0dc9db7690ca13c6c.png","timeStamp":1645800507410}],"result":"SUCCESS","precondition":false,"level":0,"children":[{"number":9,"description":"he should see text of each of the \u0027inventory_item_name\u0027 element that contains: \u003c[Sauce Labs Bike Light]\u003e","duration":30,"startTime":"2022-02-25T14:48:27.377862019Z[Etc/UTC]","screenshots":[{"screenshot":"462ede654114dbfdec5561bbe0a5b4b35c66cc9e794538f0dc9db7690ca13c6c.png","timeStamp":1645800507408}],"result":"SUCCESS","precondition":false,"level":1}]}],"userStory":{"id":"managing-the-cart","storyName":"Managing the cart","displayName":"Managing the cart","path":"cart/managing_the_cart.feature","type":"feature"},"featureTag":{"name":"Cart/Managing the cart","type":"feature","displayName":"Cart/Managing the cart"},"title":"Colin removes an item from the cart overview","description":"","backgroundTitle":"","backgroundDescription":"","tags":[{"name":"Cart","type":"capability","displayName":"Cart"},{"name":"Cart/Managing the cart","type":"feature","displayName":"Managing the cart"},{"name":"cart","type":"tag","displayName":"cart"}],"startTime":"2022-02-25T14:48:24.730691870Z[Etc/UTC]","duration":2687,"rule":{"name":"Customer can remove items from their cart","description":""},"projectKey":"","sessionId":"15287f957e7ea3249af5041c358adf85","driver":"chrome:colin","isManualTestingUpToDate":false,"manual":false,"testSource":"Cucumber","actors":[{"name":"Colin","can":["browse the web"],"has":["swaglabs.actions.cart.AShoppingCart@5d1f9d8b"]}],"result":"SUCCESS"}